<perf>
    <car mass="1313.916" inertia="528 1315 1758"/>
    <com frontPercent="60.042034" pos="0.075 0.002 -0.049" whf="1.54" whr="-1.15"/>
    <torque max="729.8916" rpm="5450" mul="1.2"/>
    <power max="601.5283" rpm="7890"/>
    <bhpPerTon val="381.51114"/>
    <top speed="454.1198" time="31.73261"/>
    <quarterMile time="8.681205" vel="288.9864"/>
    <accel t60="1.2500025" t100="2.1812525" t160="3.787478" t200="5.043709"/>
    <downForce d100="-0" d160="-0" d200="-0"/>
    <stop s160="2.4374628" s100="1.5312266" s60="0.918736"/>
    <velGraph>
        <p t="0.11" v="5.2"/>
        <p t="0.21" v="10.3"/>
        <p t="0.31" v="15.3"/>
        <p t="0.41" v="20.6"/>
        <p t="0.52" v="25.8"/>
        <p t="0.63" v="31.0"/>
        <p t="0.73" v="36.1"/>
        <p t="0.84" v="41.2"/>
        <p t="0.95" v="46.5"/>
        <p t="1.06" v="51.7"/>
        <p t="1.18" v="56.8"/>
        <p t="1.29" v="61.9"/>
        <p t="1.40" v="67.0"/>
        <p t="1.52" v="72.2"/>
        <p t="1.64" v="77.4"/>
        <p t="1.76" v="82.5"/>
        <p t="1.88" v="87.5"/>
        <p t="2.00" v="92.7"/>
        <p t="2.13" v="97.9"/>
        <p t="2.25" v="103.0"/>
        <p t="2.37" v="108.0"/>
        <p t="2.51" v="113.2"/>
        <p t="2.64" v="118.3"/>
        <p t="2.77" v="123.4"/>
        <p t="2.91" v="128.6"/>
        <p t="3.04" v="133.7"/>
        <p t="3.18" v="138.8"/>
        <p t="3.32" v="144.0"/>
        <p t="3.47" v="149.1"/>
        <p t="3.61" v="154.1"/>
        <p t="3.76" v="159.3"/>
        <p t="3.91" v="164.4"/>
        <p t="4.06" v="169.4"/>
        <p t="4.22" v="174.5"/>
        <p t="4.37" v="179.5"/>
        <p t="4.54" v="184.7"/>
        <p t="4.70" v="189.7"/>
        <p t="4.87" v="194.9"/>
        <p t="5.04" v="200.0"/>
        <p t="5.21" v="205.1"/>
        <p t="5.39" v="210.2"/>
        <p t="5.57" v="215.3"/>
        <p t="5.75" v="220.3"/>
        <p t="5.94" v="225.4"/>
        <p t="6.13" v="230.5"/>
        <p t="6.32" v="235.6"/>
        <p t="6.52" v="240.7"/>
        <p t="6.73" v="245.8"/>
        <p t="6.94" v="250.8"/>
        <p t="7.15" v="255.9"/>
        <p t="7.37" v="261.0"/>
        <p t="7.59" v="266.1"/>
        <p t="7.82" v="271.2"/>
        <p t="8.06" v="276.3"/>
        <p t="8.31" v="281.4"/>
        <p t="8.56" v="286.5"/>
        <p t="8.81" v="291.6"/>
        <p t="9.07" v="296.6"/>
        <p t="9.34" v="301.7"/>
        <p t="9.63" v="306.8"/>
        <p t="9.91" v="311.8"/>
        <p t="10.21" v="316.8"/>
        <p t="10.51" v="321.9"/>
        <p t="10.83" v="326.9"/>
        <p t="11.16" v="332.0"/>
        <p t="11.51" v="337.1"/>
        <p t="11.86" v="342.2"/>
        <p t="12.23" v="347.2"/>
        <p t="12.62" v="352.3"/>
        <p t="13.02" v="357.3"/>
        <p t="13.44" v="362.3"/>
        <p t="13.88" v="367.3"/>
        <p t="14.34" v="372.3"/>
        <p t="14.83" v="377.4"/>
        <p t="15.34" v="382.4"/>
        <p t="15.88" v="387.4"/>
        <p t="16.46" v="392.4"/>
        <p t="17.08" v="397.4"/>
        <p t="17.75" v="402.5"/>
        <p t="18.47" v="407.5"/>
        <p t="19.25" v="412.5"/>
        <p t="20.11" v="417.5"/>
        <p t="21.05" v="422.6"/>
        <p t="22.11" v="427.6"/>
        <p t="23.30" v="432.6"/>
        <p t="24.68" v="437.6"/>
        <p t="26.30" v="442.6"/>
        <p t="28.28" v="447.6"/>
        <p t="30.82" v="452.6"/>
        <p t="31.73" v="454.1"/>
    </velGraph>
</perf>
